uiucprescon/tripwire/__init__.py
uiucprescon/tripwire/__main__.py
uiucprescon/tripwire/main.py
uiucprescon/tripwire/utils.py
uiucprescon/tripwire/validation.py
uiucprescon_tripwire-0.3.0.dist-info/LICENSE
uiucprescon_tripwire-0.3.0.dist-info/METADATA
uiucprescon_tripwire-0.3.0.dist-info/WHEEL
uiucprescon_tripwire-0.3.0.dist-info/entry_points.txt
uiucprescon_tripwire-0.3.0.dist-info/top_level.txt
uiucprescon_tripwire-0.3.0.dist-info/RECORD
