Metadata-Version: 2.2
Name: uiucprescon.tripwire
Version: 0.3.0
Author-email: "University Library at The University of Illinois at Urbana Champaign: Preservation Services" <prescons@library.illinois.edu>
Maintainer-email: Henry Borchers <hborcher@illinois.edu>
License: University of Illinois/NCSA Open Source License
Project-URL: project, https://github.com/UIUCLibrary/tripwire
Requires-Python: >=3.11
License-File: LICENSE
Requires-Dist: tqdm
